LICENSE.txt
MANIFEST.in
README.rst
setup.py
django_debug_queries/__init__.py
django_debug_queries.egg-info/PKG-INFO
django_debug_queries.egg-info/SOURCES.txt
django_debug_queries.egg-info/dependency_links.txt
django_debug_queries.egg-info/requires.txt
django_debug_queries.egg-info/top_level.txt