Metadata-Version: 1.0
Name: django-debug-queries
Version: 0.0.6
Summary: A context manager for printing Django SQL queries to the terminal
Home-page: UNKNOWN
Author: Mark Longair
Author-email: mark@mysociety.org
License: MIT
Keywords: django debugging sql debug queries
Platform: UNKNOWN
